procrust/__init__.py
procrust/procrust.py
procrust-0.1.0.dist-info/LICENSE
procrust-0.1.0.dist-info/METADATA
procrust-0.1.0.dist-info/WHEEL
procrust-0.1.0.dist-info/entry_points.txt
procrust-0.1.0.dist-info/top_level.txt
procrust-0.1.0.dist-info/RECORD
