Metadata-Version: 2.1
Name: procrust
Version: 0.1.0
Summary: Limit the time you procrastinate by blocking websites via the hosts file
Home-page: https://github.com/yaph/procrust
Author: Ramiro Gómez
Author-email: code@ramiro.org
License: MIT
Platform: UNKNOWN
Classifier: Development Status :: 2 - Pre-Alpha
Classifier: License :: OSI Approved :: MIT License
Classifier: Programming Language :: Python
Classifier: Programming Language :: Python :: 3.5
Classifier: Programming Language :: Python :: 3.6
Classifier: Programming Language :: Python :: 3.7
Requires-Dist: python-hosts
